
<filesystem>

    <folder name="Actions">
        <folder name="Readers">
            <file name="org-esa-s1tbx-io-importGenericComplex.instance">
                <attr name="instanceCreate" methodvalue="org.openide.awt.Actions.alwaysEnabled"/>
                <attr name="delegate" methodvalue="org.esa.s1tbx.io.generic.ImportParameterizedProductAction.create"/>
                <attr name="displayName" stringvalue="Generic Complex"/>
                <attr name="formatName" stringvalue="Complex Binary"/>
                <attr name="useAllFileFilter" boolvalue="true"/>
                <attr name="helpId" stringvalue="importGenericComplex"/>
                <attr name="ShortDescription" stringvalue="Open Generic Complex product."/>
            </file>
            <file name="org-esa-s1tbx-io-importGenericBinary.instance">
                <attr name="instanceCreate" methodvalue="org.openide.awt.Actions.alwaysEnabled"/>
                <attr name="delegate" methodvalue="org.esa.s1tbx.io.generic.ImportParameterizedProductAction.create"/>
                <attr name="displayName" stringvalue="Generic Binary"/>
                <attr name="formatName" stringvalue="Generic Binary"/>
                <attr name="useAllFileFilter" boolvalue="true"/>
                <attr name="helpId" stringvalue="importGenericBinary"/>
                <attr name="ShortDescription" stringvalue="Open Generic Binary product."/>
            </file>
        </folder>
    </folder>

    <folder name="Menu">
        <folder name="File">
            <folder name="Import">
                <folder name="SAR Formats">
                    <file name="org-esa-s1tbx-io-importGenericComplex.shadow">
                        <attr name="originalFile" stringvalue="Actions/Readers/org-esa-s1tbx-io-importGenericComplex.instance"/>
                        <attr name="position" intvalue="400"/>
                    </file>
                    <file name="org-esa-s1tbx-io-importGenericBinary.shadow">
                        <attr name="originalFile" stringvalue="Actions/Readers/org-esa-s1tbx-io-importGenericBinary.instance"/>
                        <attr name="position" intvalue="400"/>
                    </file>
                </folder>
            </folder>
        </folder>
    </folder>

    <folder name="LayerSources">
        <file name="maptools-layer">
            <attr name="displayName" stringvalue="Mapping Tools"/>
            <attr name="description" stringvalue="Shows cartographic overlays"/>
            <attr name="layerSourceClass" stringvalue="org.esa.s1tbx.dat.layers.maptools.MapToolsLayerSource"/>
        </file>
        <file name="topsBurstLayer">
            <attr name="displayName" stringvalue="TOPS Burst Boundaries"/>
            <attr name="description" stringvalue="Shows TOPSAR burst and subswath boundaries"/>
            <attr name="layerSourceClass" stringvalue="org.esa.s1tbx.dat.layers.topsbursts.TOPSBurstLayerSource"/>
        </file>
    </folder>
    <folder name="LayerEditors">
        <file name="maptools-layer">
            <attr name="layerClass" stringvalue="org.esa.s1tbx.dat.layers.maptools.MapToolsLayer"/>
            <attr name="editorClass" stringvalue="org.esa.s1tbx.dat.layers.maptools.MapToolsLayerEditor"/>
        </file>
    </folder>

</filesystem>